asyncio_datagram/__init__.py
asyncio_datagram/aio.py
asyncio_datagram/aio.pyi
asyncio_datagram/py.typed
asyncio_datagram-1.4.0.dist-info/LICENSE
asyncio_datagram-1.4.0.dist-info/METADATA
asyncio_datagram-1.4.0.dist-info/WHEEL
asyncio_datagram-1.4.0.dist-info/top_level.txt
asyncio_datagram-1.4.0.dist-info/RECORD
