Metadata-Version: 2.1
Name: asyncio-datagram
Version: 1.4.0
Summary: Higher level Datagram support for Asyncio
Home-page: https://github.com/mishamyrt/asyncio-datagram
Author: Mikhael Khrustik
Author-email: misha@myrt.co
License: MIT
Platform: UNKNOWN
Classifier: Development Status :: 5 - Production/Stable
Classifier: Intended Audience :: Developers
Classifier: Framework :: AsyncIO
Classifier: License :: OSI Approved :: MIT License
Classifier: Programming Language :: Python :: 3.6
Classifier: Programming Language :: Python :: 3.7
Classifier: Programming Language :: Python :: 3.8
Classifier: Programming Language :: Python :: 3.9
Classifier: Programming Language :: Python :: 3.10
Classifier: Programming Language :: Python :: 3.11
Requires-Python: >=3.6
License-File: LICENSE
Requires-Dist: setuptools
Provides-Extra: test
Requires-Dist: black >=20.8b1 ; extra == 'test'
Requires-Dist: flake8 >=3.8.3 ; extra == 'test'
Requires-Dist: mypy-extensions >=0.4.3 ; extra == 'test'
Requires-Dist: mypy >=0.812 ; extra == 'test'
Requires-Dist: pytest-asyncio >=0.14.0 ; extra == 'test'
Requires-Dist: pytest >=5.4.3 ; extra == 'test'
Requires-Dist: typed-ast >=1.4.3 ; extra == 'test'
Requires-Dist: typing-extensions >=3.10.0.0 ; extra == 'test'
